devpi_web/__init__.py
devpi_web/clear_index.py
devpi_web/compat.py
devpi_web/config.py
devpi_web/description.py
devpi_web/doczip.py
devpi_web/hookspecs.py
devpi_web/indexing.py
devpi_web/macroregistry.py
devpi_web/macros.py
devpi_web/main.py
devpi_web/null_index.py
devpi_web/views.py
devpi_web/whoosh_index.py
devpi_web/static/common.js
devpi_web/static/docview.js
devpi_web/static/favicon.ico
devpi_web/static/jquery-3.6.0.min.js
devpi_web/static/search.js
devpi_web/static/style.css
devpi_web/templates/doc.pt
devpi_web/templates/error.pt
devpi_web/templates/favicon.pt
devpi_web/templates/footer.pt
devpi_web/templates/footer_versions.pt
devpi_web/templates/head.pt
devpi_web/templates/header.pt
devpi_web/templates/header_breadcrumbs.pt
devpi_web/templates/header_search.pt
devpi_web/templates/header_status.pt
devpi_web/templates/html_head_css.pt
devpi_web/templates/html_head_scripts.pt
devpi_web/templates/index.pt
devpi_web/templates/logo.pt
devpi_web/templates/notfound.pt
devpi_web/templates/project.pt
devpi_web/templates/query_docs.pt
devpi_web/templates/root.pt
devpi_web/templates/root_above_user_index_list.pt
devpi_web/templates/root_below_user_index_list.pt
devpi_web/templates/search.pt
devpi_web/templates/search_help.pt
devpi_web/templates/status.pt
devpi_web/templates/status_badge.pt
devpi_web/templates/toxresult.pt
devpi_web/templates/toxresults.pt
devpi_web/templates/user.pt
devpi_web/templates/version.pt
devpi_web-5.0.1.dist-info/licenses/LICENSE
devpi_web-5.0.1.dist-info/METADATA
devpi_web-5.0.1.dist-info/WHEEL
devpi_web-5.0.1.dist-info/entry_points.txt
devpi_web-5.0.1.dist-info/top_level.txt
devpi_web-5.0.1.dist-info/RECORD
