Metadata-Version: 2.4
Name: devpi-web
Version: 5.0.1
Summary: devpi-web: a web view for devpi-server
Maintainer-email: Florian Schulze <mail@pyfidelity.com>
License-Expression: MIT
Project-URL: Bug Tracker, https://github.com/devpi/devpi/issues
Project-URL: Changelog, https://github.com/devpi/devpi/blob/main/web/CHANGELOG
Project-URL: Documentation, https://doc.devpi.net
Project-URL: Homepage, https://devpi.net
Project-URL: Source Code, https://github.com/devpi/devpi
Classifier: Development Status :: 5 - Production/Stable
Classifier: Environment :: Web Environment
Classifier: Intended Audience :: Developers
Classifier: Intended Audience :: System Administrators
Classifier: Programming Language :: Python
Classifier: Programming Language :: Python :: 3 :: Only
Classifier: Programming Language :: Python :: 3.9
Classifier: Programming Language :: Python :: 3.10
Classifier: Programming Language :: Python :: 3.11
Classifier: Programming Language :: Python :: 3.12
Classifier: Programming Language :: Python :: 3.13
Classifier: Programming Language :: Python :: Implementation :: PyPy
Classifier: Topic :: Internet :: WWW/HTTP
Classifier: Topic :: Internet :: WWW/HTTP :: WSGI :: Application
Requires-Python: >=3.9
License-File: LICENSE
Requires-Dist: Whoosh<3
Requires-Dist: attrs>=22.2.0
Requires-Dist: beautifulsoup4!=4.12.1,>=4.3.2
Requires-Dist: defusedxml
Requires-Dist: devpi-server>=6.13.0
Requires-Dist: devpi-common>=4.0.0
Requires-Dist: docutils>=0.11
Requires-Dist: pygments>=1.6
Requires-Dist: pyramid>=2
Requires-Dist: pyramid-chameleon
Requires-Dist: readme-renderer[md]>=23.0
Requires-Dist: tomli; python_version < "3.11"
Dynamic: license-file
